sns_message_validator/__init__.py
sns_message_validator/exceptions.py
sns_message_validator/sns_message_type.py
sns_message_validator/sns_message_validator.py
sns_message_validator-0.0.1.dist-info/LICENSE
sns_message_validator-0.0.1.dist-info/METADATA
sns_message_validator-0.0.1.dist-info/WHEEL
sns_message_validator-0.0.1.dist-info/top_level.txt
sns_message_validator-0.0.1.dist-info/RECORD
