Metadata-Version: 2.1
Name: sns-message-validator
Version: 0.0.1
Summary: Validator for SNS messages.
Home-page: https://github.com/debanjan97/sns-message-validator
Author: https://github.com/wlwg
License: UNKNOWN
Platform: UNKNOWN
Requires-Python: >=3.6
Requires-Dist: cryptography (==2.6.1)
Requires-Dist: requests (==2.21.0)
